searchgpy/__init__.py
searchgooglepy-0.0.5.dist-info/METADATA
searchgooglepy-0.0.5.dist-info/WHEEL
searchgooglepy-0.0.5.dist-info/licenses/AUTHORS.md
searchgooglepy-0.0.5.dist-info/licenses/LICENSE
searchgooglepy-0.0.5.dist-info/RECORD
