Metadata-Version: 2.1
Name: SearchGooglePy
Version: 0.0.5
Summary: SearchGooglePy is a simple (un-official) Google Search API under python.
Project-URL: Homepage, https://boubajoker.github.io/SearchGooglePy/
Project-URL: Bug Tracker, https://github.com/Boubajoker/SearchGooglePy/
Author-email: Boubajoker <mohanathas.leo@gmail.com>
License: MIT License
Classifier: License :: OSI Approved :: MIT License
Classifier: Operating System :: OS Independent
Classifier: Programming Language :: Python :: 3
Requires-Python: >=3.7
